LICENSE.txt
README.md
setup.py
src/honichi/__init__.py
src/honichi/honichi.py
src/honichi.egg-info/PKG-INFO
src/honichi.egg-info/SOURCES.txt
src/honichi.egg-info/dependency_links.txt
src/honichi.egg-info/entry_points.txt
src/honichi.egg-info/top_level.txt