Metadata-Version: 2.1
Name: honichi
Version: 0.1.0
Summary: Show the number of tourists coming to Japan
Home-page: https://github.com/HaiBunn/honichi/blob/main/README.md
Author: ouekii
Author-email: s2122010@stu.musashino-u.ac.jp
Project-URL: Bug Tracker, https://github.com/HaiBunn/honichi
Classifier: Programming Language :: Python :: 3
Classifier: License :: OSI Approved :: MIT License
Classifier: Operating System :: OS Independent
Requires-Python: >=3.8
License-File: LICENSE.txt
